ipc_sun_sync/__init__.py
ipc_sun_sync/constants.py
ipc_sun_sync/dahua_cgi.py
ipc_sun_sync/dahua_rpc.py
ipc_sun_sync/exceptions.py
ipc_sun_sync/main.py
ipc_sun_sync/parser.py
ipc_sun_sync/utils.py
ipc_sun_sync-0.2.3.dist-info/entry_points.txt
ipc_sun_sync-0.2.3.dist-info/LICENSE
ipc_sun_sync-0.2.3.dist-info/WHEEL
ipc_sun_sync-0.2.3.dist-info/METADATA
ipc_sun_sync-0.2.3.dist-info/RECORD
