Metadata-Version: 2.1
Name: ipc-sun-sync
Version: 0.2.3
Summary: Sync sunrise and sunset on Dahua IP cameras.
License: MIT
Author: ItsNotGoodName
Author-email: gurnaindeol@gmail.com
Requires-Python: >=3.7.2,<4.0.0
Classifier: License :: OSI Approved :: MIT License
Classifier: Operating System :: OS Independent
Classifier: Programming Language :: Python :: 3
Classifier: Programming Language :: Python :: 3.8
Classifier: Programming Language :: Python :: 3.9
Classifier: Programming Language :: Python :: 3.10
Classifier: Programming Language :: Python :: 3
Requires-Dist: PyYAML (>=6.0,<7.0)
Requires-Dist: astral (>=2.2,<3.0)
Requires-Dist: pytimeparse (>=1.1.8,<2.0.0)
Requires-Dist: pytz (==2022.1)
Requires-Dist: requests (>=2.28.0,<3.0.0)
